jupyter_nbutils/__about__.py
jupyter_nbutils/__init__.py
jupyter_nbutils/config.py
jupyter_nbutils/utils.py
jupyter_nbutils/warnings.py
jupyter_nbutils-0.1.3.dist-info/LICENSE
jupyter_nbutils-0.1.3.dist-info/METADATA
jupyter_nbutils-0.1.3.dist-info/WHEEL
jupyter_nbutils-0.1.3.dist-info/top_level.txt
jupyter_nbutils-0.1.3.dist-info/RECORD
