Metadata-Version: 2.1
Name: jupyter-nbutils
Version: 0.1.3
Summary: A collection of Jupyter notebook tools and utilities.
Home-page: https://github.com/CermakM/jupyter-nbutils
Author: Marek Cermak
Author-email: macermak@redhat.com
License: MIT
Platform: UNKNOWN
Classifier: Development Status :: 2 - Pre-Alpha
Classifier: Framework :: IPython
Classifier: Framework :: Jupyter
Classifier: License :: OSI Approved :: MIT License
Classifier: Natural Language :: English
Classifier: Operating System :: OS Independent
Classifier: Programming Language :: JavaScript
Classifier: Programming Language :: Python :: 3.6
Classifier: Programming Language :: Python :: 3.7
Classifier: Topic :: Scientific/Engineering :: Visualization
Classifier: Topic :: Utilities
